pyglslify.py
pyglslify-0.1.1.dist-info/LICENSE
pyglslify-0.1.1.dist-info/WHEEL
pyglslify-0.1.1.dist-info/METADATA
pyglslify-0.1.1.dist-info/RECORD
