Metadata-Version: 2.1
Name: pyglslify
Version: 0.1.1
Summary: Thin wrapper for the glslify nodejs tool, use stack.gl shader modules in Python.
Home-page: https://github.com/anentropic/pyglslify
License: MIT
Author: Anentropic
Author-email: ego@anentropic.com
Requires-Python: >=3.6
Classifier: License :: OSI Approved :: MIT License
Classifier: Programming Language :: Python :: 3
Classifier: Programming Language :: Python :: 3.6
Classifier: Programming Language :: Python :: 3.7
Classifier: Programming Language :: Python :: 3.8
Classifier: Programming Language :: Python :: 3.9
